{
    "education_fields": {
        "Computer Science": "Computer Science",
        "Computer Science \u0026 Software Engineering": "Computer Science",
        "Computer science": "Computer Science",
        "IT": "Software Engineering",
        "Industrial engineering and management": "Industrial engineering",
        "Information Technology": "Software Engineering",
        "Information Technology / Interaction Design": "Interaction Design",
        "Software Engineering": "Software Engineering",
        "Software Engineering/Computer Science": "Software Engineering",
        "Software engineering": "Software Engineering",
        "Software engingeering": "Software Engineering",
        "civil engineering": "Civil Engineering",
        "computer science": "Computer Science",
        "electrical engineering": "Electrical Engineering",
        "none": "None",
        "software engineering": "Software Engineering"
    },
    "work_domains": {
        "-": "None",
        "0": "None",
        "1": "None",
        "Adtech": "Adtech",
        "Android": "App",
        "Automotive": "Automotive",
        "Developing full-stack websites": "Web",
        "Finance": "Finance",
        "Government": "Government",
        "Have not": "None",
        "Marketing": "Marketing",
        "Mobility": "Automotive",
        "N/A": "None",
        "None": "None",
        "School, which I don't count as professional experience.": "None",
        "Software development": "Mixed",
        "Telecom": "Telecom",
        "University": "None",
        "Vehicle industry": "Automotive",
        "Web development": "Web",
        "Web-development": "Web",
        "Webdevelopment": "Web",
        "android development": "App",
        "automotive": "Automotive",
        "devops": "Devops",
        "e-commerce": "E-Commerce",
        "e-commerce, e-health": "E-Commerce",
        "financial": "Finance",
        "mixed": "Mixed",
        "music industry": "Music",
        "no work experience": "None",
        "radar": "Embedded",
        "research": "Research",
        "retail": "Retail",
        "telecom": "Telecom",
        "web development": "Web",
        "webb": "Web",
        "webdevelopment": "Web"
    },
    "signup_codes": {
        "cup-cd": "consultants",
        "kiwi-steel": "product-company",
        "light-card": "consultants",
        "lock-cable": "friends",
        "power-pillow": "open",
        "prestudy-students": "students",
        "ring-button": "code-interested",
        "screen-floor": "open",
        "tv-box": "professional-contact"
    }
}